langchain_privy/__init__.py
langchain_privy/auth.py
langchain_privy/chains.py
langchain_privy/exceptions.py
langchain_privy/rpc_client.py
langchain_privy/utils.py
langchain_privy/wallet_tool.py
langchain_privy-0.1.0.dist-info/METADATA
langchain_privy-0.1.0.dist-info/WHEEL
langchain_privy-0.1.0.dist-info/licenses/LICENSE
langchain_privy-0.1.0.dist-info/RECORD
