Metadata-Version: 2.4
Name: langchain-privy
Version: 0.1.0
Summary: LangChain integration for Privy embedded wallets
Project-URL: Homepage, https://github.com/privy-io/privy
Project-URL: Documentation, https://docs.privy.io
Project-URL: Repository, https://github.com/privy-io/privy
Author-email: Privy <support@privy.io>
License: MIT
License-File: LICENSE
Keywords: ai-agents,blockchain,langchain,privy,wallets,web3
Classifier: Development Status :: 3 - Alpha
Classifier: Intended Audience :: Developers
Classifier: License :: OSI Approved :: MIT License
Classifier: Programming Language :: Python :: 3
Classifier: Programming Language :: Python :: 3.9
Classifier: Programming Language :: Python :: 3.10
Classifier: Programming Language :: Python :: 3.11
Classifier: Programming Language :: Python :: 3.12
Classifier: Topic :: Software Development :: Libraries :: Python Modules
Requires-Python: >=3.9
Requires-Dist: langchain-core>=0.1.0
Requires-Dist: pydantic>=2.0.0
Requires-Dist: requests>=2.31.0
Requires-Dist: tenacity>=8.0.0
Provides-Extra: dev
Requires-Dist: black>=23.7.0; extra == 'dev'
Requires-Dist: mypy>=1.5.0; extra == 'dev'
Requires-Dist: pytest-asyncio>=0.21.0; extra == 'dev'
Requires-Dist: pytest-mock>=3.11.1; extra == 'dev'
Requires-Dist: pytest>=7.4.0; extra == 'dev'
Requires-Dist: ruff>=0.0.287; extra == 'dev'
